spatial_grouping_attention/__init__.py
spatial_grouping_attention/spatial_grouping_attention.py
spatial_grouping_attention/utils.py
spatial_grouping_attention-2025.9.29.1947.dist-info/METADATA
spatial_grouping_attention-2025.9.29.1947.dist-info/WHEEL
spatial_grouping_attention-2025.9.29.1947.dist-info/licenses/LICENSE
spatial_grouping_attention-2025.9.29.1947.dist-info/RECORD
