Metadata-Version: 2.4
Name: spatial-grouping-attention
Version: 2025.9.29.1947
Summary: PyTorch Implementation of Spatial Grouping Attention Layer
Project-URL: Homepage, https://github.com/rhoadesScholar/spatial-grouping-attention
Project-URL: Repository, https://github.com/rhoadesScholar/spatial-grouping-attention
Project-URL: Documentation, https://github.com/rhoadesScholar/spatial-grouping-attention
Project-URL: Issues, https://github.com/rhoadesScholar/spatial-grouping-attention/issues
Author-email: Jeff Rhoades <rhoadesj@hhmi.org>
Maintainer-email: Jeff Rhoades <rhoadesj@hhmi.org>
License: BSD 3-Clause License
License-File: LICENSE
Keywords: attention,rotary spatial embedding,segmentation,spatial grouping,transformer
Classifier: Development Status :: 4 - Beta
Classifier: Intended Audience :: Developers
Classifier: Intended Audience :: Science/Research
Classifier: License :: OSI Approved :: BSD License
Classifier: Operating System :: OS Independent
Classifier: Programming Language :: Python :: 3
Classifier: Programming Language :: Python :: 3.10
Classifier: Programming Language :: Python :: 3.11
Classifier: Programming Language :: Python :: 3.12
Classifier: Topic :: Scientific/Engineering
Classifier: Topic :: Software Development :: Libraries :: Python Modules
Requires-Python: >=3.10
Requires-Dist: cmake
Requires-Dist: ninja
Requires-Dist: rotary-spatial-embeddings>=2025.9.25.1502
Requires-Dist: timm
Requires-Dist: torch[opt-einsum]
Provides-Extra: dev
Requires-Dist: black>=22.0; extra == 'dev'
Requires-Dist: flake8>=4.0; extra == 'dev'
Requires-Dist: isort>=5.0; extra == 'dev'
Requires-Dist: mypy>=0.900; extra == 'dev'
Requires-Dist: pre-commit>=2.0; extra == 'dev'
Requires-Dist: pytest-cov>=2.0; extra == 'dev'
Requires-Dist: pytest-xdist>=2.0; extra == 'dev'
Requires-Dist: pytest>=6.0; extra == 'dev'
Provides-Extra: docs
Requires-Dist: myst-parser>=0.15; extra == 'docs'
Requires-Dist: sphinx-rtd-theme>=1.0; extra == 'docs'
Requires-Dist: sphinx>=4.0; extra == 'docs'
Provides-Extra: lint
Requires-Dist: black>=22.0; extra == 'lint'
Requires-Dist: flake8>=4.0; extra == 'lint'
Requires-Dist: isort>=5.0; extra == 'lint'
Requires-Dist: mypy>=0.900; extra == 'lint'
Provides-Extra: test
Requires-Dist: pytest-cov>=2.0; extra == 'test'
Requires-Dist: pytest-xdist>=2.0; extra == 'test'
Requires-Dist: pytest>=6.0; extra == 'test'
